setup.py
liuzhenyuisagoodsman/__init__.py
liuzhenyuisagoodsman/yiyatong.py
liuzhenyuisagoodsman.egg-info/PKG-INFO
liuzhenyuisagoodsman.egg-info/SOURCES.txt
liuzhenyuisagoodsman.egg-info/dependency_links.txt
liuzhenyuisagoodsman.egg-info/not-zip-safe
liuzhenyuisagoodsman.egg-info/top_level.txt