Metadata-Version: 1.0
Name: liuzhenyuisagoodsman
Version: 0.1
Summary: The funniest joke in the world
Home-page: http://github.com/storborg/funniest
Author: liu
Author-email: liu@example.com
License: MIT
Platform: UNKNOWN
